yaogua/__init__.py
yaogua/__main__.py
yaogua/gui.py
yaogua/yaogua.json
yaogua/yaogua_rc.py
yaogua/zhouyi.py
yaogua/html_resource/bootstrap.min.css
yaogua/html_resource/bootstrap.min.js
yaogua/html_resource/elegant.css
yaogua/html_resource/font-awesome.css
yaogua/html_resource/jquery.min.js
yaogua/html_resource/moment.min.js
yaogua/html_resource/yaogua.js
yaogua/html_resource/zhou_yi_yao_gua.html
yaogua-0.1.0.dist-info/LICENSE
yaogua-0.1.0.dist-info/METADATA
yaogua-0.1.0.dist-info/WHEEL
yaogua-0.1.0.dist-info/entry_points.txt
yaogua-0.1.0.dist-info/top_level.txt
yaogua-0.1.0.dist-info/RECORD
