Metadata-Version: 2.1
Name: yaogua
Version: 0.1.0
Summary: a simple command line tool for zhouyi yaogua.
Home-page: https://github.com/a358003542/yaogua
Author: wanze
Author-email: a358003542@gmail.com
Maintainer: wanze
Maintainer-email: a358003542@gmail.com
License: MIT
Keywords: zhouyi,python
Platform: Linux
Platform: windows
Classifier: License :: OSI Approved :: MIT License
Classifier: Operating System :: Microsoft
Classifier: Operating System :: POSIX :: Linux
Classifier: Programming Language :: Python :: 3
Requires-Dist: click
